CHANGELOG.md
README.md
complio/__init__.py
complio/cli/__init__.py
complio/cli/banner.py
complio/cli/commands/__init__.py
complio/cli/commands/activate.py
complio/cli/commands/deactivate.py
complio/cli/commands/history.py
complio/cli/commands/license_info.py
complio/cli/commands/scan.py
complio/cli/main.py
complio/cli/output.py
complio/config/__init__.py
complio/config/settings.py
complio/connectors/__init__.py
complio/connectors/aws/__init__.py
complio/connectors/aws/client.py
complio/connectors/base.py
complio/core/__init__.py
complio/core/registry.py
complio/core/runner.py
complio/licensing/__init__.py
complio/licensing/exceptions.py
complio/licensing/models.py
complio/licensing/validator.py
complio/py.typed
complio/reporters/__init__.py
complio/reporters/generator.py
complio/tests_library/__init__.py
complio/tests_library/base.py
complio/tests_library/identity/__init__.py
complio/tests_library/identity/access_key_rotation.py
complio/tests_library/identity/mfa_enforcement.py
complio/tests_library/identity/root_account_protection.py
complio/tests_library/infrastructure/__init__.py
complio/tests_library/infrastructure/cloudtrail_encryption.py
complio/tests_library/infrastructure/cloudtrail_log_validation.py
complio/tests_library/infrastructure/cloudtrail_logging.py
complio/tests_library/infrastructure/ebs_encryption.py
complio/tests_library/infrastructure/ec2_security_groups.py
complio/tests_library/infrastructure/iam_password_policy.py
complio/tests_library/infrastructure/nacl_security.py
complio/tests_library/infrastructure/rds_encryption.py
complio/tests_library/infrastructure/s3_encryption.py
complio/tests_library/infrastructure/s3_public_access.py
complio/tests_library/infrastructure/secrets_manager_encryption.py
complio/tests_library/infrastructure/vpc_flow_logs.py
complio/tests_library/logging/__init__.py
complio/tests_library/logging/cloudwatch_alarms.py
complio/tests_library/logging/cloudwatch_logs_encryption.py
complio-0.1.0.dist-info/METADATA
complio-0.1.0.dist-info/WHEEL
complio-0.1.0.dist-info/entry_points.txt
complio-0.1.0.dist-info/RECORD
