Metadata-Version: 2.1
Name: complio
Version: 0.1.0
Summary: Compliance-as-Code Platform - Automated ISO 27001 infrastructure compliance testing for AWS
Home-page: https://complio.tech
License: MIT
Keywords: compliance,iso27001,soc2,aws,security,devops,infrastructure,audit,governance,cloud-security
Author: Complio Team
Author-email: team@compl.io
Maintainer: Complio Team
Maintainer-email: team@compl.io
Requires-Python: >=3.11,<4.0
Classifier: Development Status :: 3 - Alpha
Classifier: Environment :: Console
Classifier: Intended Audience :: Developers
Classifier: Intended Audience :: Information Technology
Classifier: Intended Audience :: System Administrators
Classifier: License :: OSI Approved :: MIT License
Classifier: Operating System :: OS Independent
Classifier: Programming Language :: Python :: 3
Classifier: Programming Language :: Python :: 3.11
Classifier: Programming Language :: Python :: 3.12
Classifier: Topic :: Security
Classifier: Topic :: Software Development :: Quality Assurance
Classifier: Topic :: System :: Monitoring
Classifier: Typing :: Typed
Requires-Dist: boto3 (>=1.34.0,<2.0.0)
Requires-Dist: botocore (>=1.34.0,<2.0.0)
Requires-Dist: click (>=8.1.7,<9.0.0)
Requires-Dist: cryptography (>=42.0.0,<43.0.0)
Requires-Dist: jinja2 (>=3.1.3,<4.0.0)
Requires-Dist: markdown (>=3.5.2,<4.0.0)
Requires-Dist: pydantic (>=2.5.3,<3.0.0)
Requires-Dist: pydantic-settings (>=2.1.0,<3.0.0)
Requires-Dist: python-dateutil (>=2.8.2,<3.0.0)
Requires-Dist: python-json-logger (>=2.0.7,<3.0.0)
Requires-Dist: pyyaml (>=6.0.1,<7.0.0)
Requires-Dist: reportlab (>=4.0.9,<5.0.0)
Requires-Dist: requests (>=2.31.0,<3.0.0)
Requires-Dist: rich (>=13.7.0,<14.0.0)
Requires-Dist: structlog (>=24.1.0,<25.0.0)
Project-URL: Documentation, https://docs.complio.tech
Project-URL: Repository, https://github.com/complio/complio
